drf_httpsig/__init__.py
drf_httpsig/authentication.py
drf_httpsig/tests.py
drf_httpsig-1.2.0.dist-info/DESCRIPTION.rst
drf_httpsig-1.2.0.dist-info/METADATA
drf_httpsig-1.2.0.dist-info/RECORD
drf_httpsig-1.2.0.dist-info/WHEEL
drf_httpsig-1.2.0.dist-info/metadata.json
drf_httpsig-1.2.0.dist-info/top_level.txt
drf_httpsig-1.2.0.dist-info/zip-safe
