Metadata-Version: 2.0
Name: drf-httpsig
Version: 1.2.0
Summary: HTTP Signature support for Django REST framework
Home-page: https://github.com/ahknight/drf-httpsig
Author: Adam Knight
Author-email: adam@movq.us
License: MIT
Platform: UNKNOWN
Classifier: Development Status :: 5 - Production/Stable
Classifier: Environment :: Web Environment
Classifier: Framework :: Django
Classifier: Intended Audience :: Developers
Classifier: License :: OSI Approved :: MIT License
Classifier: Operating System :: OS Independent
Classifier: Programming Language :: Python
Classifier: Programming Language :: Python :: 2.7
Classifier: Programming Language :: Python :: 3.3
Classifier: Programming Language :: Python :: 3.4
Classifier: Topic :: Internet :: WWW/HTTP
Classifier: Topic :: Software Development :: Libraries :: Python Modules
Requires-Dist: djangorestframework (<3)
Requires-Dist: django (<=1.7)
Requires-Dist: httpsig (<2)
